opentelemetry/semconv_ai/__init__.py
opentelemetry/semconv_ai/genai_entry.md
opentelemetry/semconv_ai/genai_entry.py
opentelemetry/semconv_ai/utils.py
opentelemetry/semconv_ai/version.py
tapm_semantic_conventions_ai-0.4.12.dist-info/METADATA
tapm_semantic_conventions_ai-0.4.12.dist-info/WHEEL
tapm_semantic_conventions_ai-0.4.12.dist-info/RECORD
